<class name="TextureFrame" inherits="Control" category="Core"><brief_description>
	Control Frame that draws a texture.</brief_description><description>
	Control frame that simply draws an assigned texture. It can stretch or not. It's a simple way to just show an image in a UI.</description><methods><method name="get_modulate" qualifiers="const"><return type="Color"></return><description></description></method><method name="get_texture" qualifiers="const"><return type="Object"></return><description></description></method><method name="has_expand" qualifiers="const"><return type="bool"></return><description></description></method><method name="set_expand"><argument index="0" name="enable" type="bool"></argument><description></description></method><method name="set_modulate"><argument index="0" name="modulate" type="Color"></argument><description></description></method><method name="set_texture"><argument index="0" name="texture" type="Object"></argument><description></description></method></methods><constants></constants></class>